angda/__init__.py
angda/__main__.py
angda/apis.py
angda/items/__init__.py
angda/items/dice.py
angda/items/roll.py
angda/tools/__init__.py
angda/tools/clui.py
angda/tools/nota.py
angda/tools/rand.py
angda-0.1.0.dist-info/METADATA
angda-0.1.0.dist-info/WHEEL
angda-0.1.0.dist-info/entry_points.txt
angda-0.1.0.dist-info/license.md
angda-0.1.0.dist-info/top_level.txt
angda-0.1.0.dist-info/zip-safe
angda-0.1.0.dist-info/RECORD
