Metadata-Version: 2.1
Name: angda
Version: 0.1.0
Summary: A neat generic dice API.
Home-page: https://angda.org
Author: Stephen Malone
Author-email: mail@angda.org
License: UNKNOWN
Project-URL: Repository, https://bitbucket.org/angda/angda
Project-URL: Bug Tracker, https://bitbucket.org/angda/angda/issues?status=new&status=open
Platform: UNKNOWN
Classifier: Development Status :: 3 - Alpha
Classifier: Environment :: Console
Classifier: Intended Audience :: End Users/Desktop
Classifier: License :: OSI Approved :: BSD License
Classifier: Natural Language :: English
Classifier: Programming Language :: Python :: 3.7
Classifier: Programming Language :: Python :: 3 :: Only
Classifier: Topic :: Games/Entertainment
